pycodec2.libs/libcodec2-ccc5ceec.so.1.2
pycodec2/__init__.py
pycodec2/pycodec2.c
pycodec2/pycodec2.cpython-312-aarch64-linux-gnu.so
pycodec2/pycodec2.pyx
pycodec2/codec2.pxd
pycodec2-4.1.0.dist-info/RECORD
pycodec2-4.1.0.dist-info/WHEEL
pycodec2-4.1.0.dist-info/METADATA
pycodec2-4.1.0.dist-info/top_level.txt
pycodec2-4.1.0.dist-info/licenses/LICENSE
