Metadata-Version: 2.4
Name: pycodec2
Version: 4.1.0
Summary: A Cython wrapper for codec2
Home-page: https://github.com/gregorias/pycodec2
Author: Grzegorz Milka
Author-email: grzegorzmilka@gmail.com
Keywords: codec2,audio,voice,speech
Classifier: Topic :: Multimedia :: Sound/Audio :: Speech
Classifier: License :: OSI Approved :: BSD License
Classifier: Programming Language :: Python :: 3
Classifier: Development Status :: 5 - Production/Stable
Requires-Python: >=3.10
License-File: LICENSE
Requires-Dist: numpy<3.0.0,>=2.00
Dynamic: author
Dynamic: author-email
Dynamic: home-page
Dynamic: license-file
